FIR_tap64.sv
`default_nettype none
`include "RTL.svh"

module multiplier #(
    parameter WIDTH = 10
) (
    input clk,
    input rst_n,
    input signed [WIDTH-1:0] data_in1,
    input signed [WIDTH-1:0] data_in2,
    output signed [WIDTH-1:0] mul_out
);
    logic signed [WIDTH+WIDTH-1:0] mul_reg;

    always_ff @(posedge clk or negedge rst_n) begin
      if (!rst_n) begin
        mul_reg <= '0;
      end else begin
        mul_reg <= data_in1 * data_in2;
      end
    end

    assign mul_out = mul_reg;
endmodule

module summer #(
    parameter WIDTH = 10
) (
    input clk,
    input rst_n,
    input signed [WIDTH-1:0] data_in1,
    input signed [WIDTH:0] data_in2,
    output signed [WIDTH-1:0] sum_out
);
    logic signed [WIDTH-1:0] sum_reg;

    always_ff @(posedge clk or negedge rst_n) begin
          if (!rst_n) begin
            sum_reg <= '0;
          end else begin
            sum_reg <= (data_in1 + data_in2);
          end
        end    
    
    assign sum_out = sum_reg;
endmodule

module FIR_TAP64 #(
    parameter NUMBER_OF_TAPS = 8,
    parameter DATA_WIDTH = 10
) (
    input logic clk,
    input logic rst_n,
    input signed [DATA_WIDTH-1:0] data_in,
    input signed [DATA_WIDTH-1:0] h [0:NUMBER_OF_TAPS-1],
    output signed [DATA_WIDTH-1:0] data_out
);
    logic signed [DATA_WIDTH+DATA_WIDTH-1:0] product [0:NUMBER_OF_TAPS-1];
    logic signed [DATA_WIDTH-1:0] delay_line [0:NUMBER_OF_TAPS-1];
    logic signed [DATA_WIDTH-1:0] data_in_reg;
    logic signed [DATA_WIDTH-1:0] sum [0:NUMBER_OF_TAPS-1];
    logic signed [DATA_WIDTH-1:0] accumulator;
    localparam DIVISOR = 2**DATA_WIDTH-1;

    logic en = 1;

    always_ff @( posedge clk or negedge rst_n ) begin
      if (!rst_n) begin
        data_in_reg <= '0;
      end else begin
          data_in_reg <= data_in;
      end
    end
    
    `FF(data_in_reg, delay_line[0], clk, en, rst_n, '0);
    assign product[0] = h[0] * data_in_reg; 
    assign sum[0] = product[0];

    genvar i;
    generate
      for(i=1; i<NUMBER_OF_TAPS; i=i+1) begin
        `FF(delay_line[i-1], delay_line[i], clk, en, rst_n, '0);
        multiplier mul0 (.clk(clk), .rst_n(rst_n), .data_in1(h[i]), .data_in2(delay_line[i]), .mul_out(product[i]));
        summer sum0 (.clk(clk), .rst_n(rst_n), .data_in1(product[i]), .data_in2(sum[i-1]), .sum_out(sum[i]));
      end
    endgenerate

    
    assign data_out = sum[NUMBER_OF_TAPS-1];
    
endmodule

tb.sv
`include "FIR_tap64.sv"
// AGBOOLA TOLULOPE 

module FIR64_tb ();
    parameter NUMBER_OF_TAPS = 63;
    parameter DATA_WIDTH = 10;
    logic clk = 0;
    logic rst_n;
    logic signed [DATA_WIDTH-1:0] data_in;
    logic signed [DATA_WIDTH-1:0] data_out;
    logic signed [DATA_WIDTH-1:0] h [0:NUMBER_OF_TAPS-1];
    int i;
    int file;
    

    logic signed [DATA_WIDTH-1:0] data_in_import [0:1999];

    FIR_TAP64 #(.NUMBER_OF_TAPS(NUMBER_OF_TAPS), .DATA_WIDTH(DATA_WIDTH)) FIR_0 (
        .clk(clk),
        .rst_n(rst_n),
        .h(h),
        .data_in(data_in),
        .data_out(data_out)
    );

    always begin
        #10 clk = ~clk;
        $fwrite(file, "%h\n", FIR64_tb.data_out);
    end

    initial begin
        for ( i=0 ; i<1999; i++) begin
            #10 data_in = data_in_import[i];
        end
    end

    initial begin
      #10 $readmemh("./filter_taps.hex", h);
    end

    initial begin       
       rst_n = 0;
       #10;
       rst_n = 1;
        file = $fopen("./output.hex", "w");
        $readmemh("./input_samples.hex", data_in_import);
        $monitor("Output Data=%h, Input Data=%h", data_out, data_in);
        #21300 $finish;
    end

    initial begin
        $dumpfile("fir64.vcd");
        $dumpvars(0, FIR64_tb.clk, FIR64_tb.rst_n, FIR64_tb.data_in, FIR64_tb.data_out);
    end

    // initial begin
    //     file = $fopen("./output.hex", "w");
    //     $fwrite(file, "%h", FIR64_tb.data_out);
    // end
endmodule

fir64.vcd
$date
	Mon Oct 02 20:00:20 2023
$end
$version
	Icarus Verilog
$end
$timescale
	1s
$end
$scope module FIR64_tb $end
$var reg 1 ! clk $end
$upscope $end
$scope module FIR64_tb $end
$var reg 1 " rst_n $end
$upscope $end
$scope module FIR64_tb $end
$var reg 10 # data_in [9:0] $end
$upscope $end
$scope module FIR64_tb $end
$var wire 10 $ data_out [9:0] $end
$upscope $end
$enddefinitions $end
$comment Show the parameter values. $end
$dumpall
$end
#0
$dumpvars
b0 $
bx #
0"
0!
$end
#10
1"
1!
#20
b11111001 #
0!
#30
b1001011 #
1!
#40
b1100110101 #
0!
#50
b1110000111 #
1!
#60
b1111111 #
0!
#70
b1111001 #
1!
#80
b1111001100 #
0!
#90
b1110110101 #
1!
#100
b110 #
0!
#110
b0 #
1!
#120
b1111111010 #
0!
#130
b1001011 #
1!
#140
b110100 #
0!
#150
b1110000111 #
1!
#160
b1110000000 #
0!
#170
b1111001 #
1!
#180
b11001011 #
0!
#190
b1110110101 #
1!
#200
b1100000111 #
0!
#210
b0 #
1!
#220
b11111001 #
0!
#230
b1001011 #
1!
#240
b1100110101 #
0!
#250
b1110000111 #
1!
#260
b10000000 #
0!
#270
b1111001 #
1!
#280
b1111001100 #
0!
#290
b1110110101 #
1!
#300
b110 #
0!
#310
b0 #
1!
#320
b1111111010 #
0!
#330
b1001011 #
1!
#340
b110100 #
0!
#350
b1110000111 #
1!
#360
b1110000001 #
0!
#370
b1111001 #
1!
#380
b11001011 #
0!
#390
b1110110101 #
1!
#400
b1100000111 #
0!
#410
b0 #
1!
#420
b11111001 #
0!
#430
b1001011 #
1!
#440
b1100110101 #
0!
#450
b1110000111 #
1!
#460
b1111111 #
0!
#470
b1111001 #
1!
#480
b1111001100 #
0!
#490
b1110110101 #
1!
#500
b110 #
0!
#510
b0 #
1!
#520
b1111111010 #
0!
#530
b1001011 #
1!
#540
b110100 #
0!
#550
b1110000111 #
1!
#560
b1110000001 #
0!
#570
b1111001 #
1!
#580
b11001011 #
0!
#590
b1110110101 #
1!
#600
b1100000111 #
0!
#610
b0 #
1!
#620
b11111001 #
0!
#630
b1001011 #
1!
#640
b1100110101 #
0!
#650
b1110000111 #
1!
#660
b10000000 #
0!
#670
b1111001 #
1!
#680
b1111001100 #
0!
#690
b1110110101 #
1!
#700
b110 #
0!
#710
b0 #
1!
#720
b1111111010 #
0!
#730
b1001011 #
1!
#740
b110100 #
0!
#750
b1110000111 #
1!
#760
b1110000001 #
0!
#770
b1111001 #
1!
#780
b11001011 #
0!
#790
b1110110101 #
1!
#800
b1100000111 #
0!
#810
b0 #
1!
#820
b11111001 #
0!
#830
b1001011 #
1!
#840
b1100110101 #
0!
#850
b1110000111 #
1!
#860
b10000000 #
0!
#870
b1111001 #
1!
#880
b1111001100 #
0!
#890
b1110110101 #
1!
#900
b110 #
0!
#910
b0 #
1!
#920
b1111111010 #
0!
#930
b1001011 #
1!
#940
b110100 #
0!
#950
b1110000111 #
1!
#960
b1110000001 #
0!
#970
b1111001 #
1!
#980
b11001011 #
0!
#990
b1110110101 #
1!
#1000
b1100000111 #
0!
#1010
b0 #
1!
#1020
b11111001 #
0!
#1030
b1001011 #
1!
#1040
b1100110101 #
0!
#1050
b1110000111 #
1!
#1060
b10000000 #
0!
#1070
b1111001 #
1!
#1080
b1111001100 #
0!
#1090
b1110110101 #
1!
#1100
b110 #
0!
#1110
b0 #
1!
#1120
b1111111010 #
0!
#1130
b1001011 #
1!
#1140
b110100 #
0!
#1150
b1110000111 #
1!
#1160
b1110000001 #
0!
#1170
b1111001 #
1!
#1180
b11001011 #
0!
#1190
b1110110101 #
1!
#1200
b1100000111 #
0!
#1210
b0 #
1!
#1220
b11111001 #
0!
#1230
bx $
b1001011 #
1!
#1240
b1100110101 #
0!
#1250
b1110000111 #
1!
#1260
b10000000 #
0!
#1270
b0 $
b1111001 #
1!
#1280
b1111001100 #
0!
#1290
b1110110101 #
1!
#1300
b110 #
0!
#1310
bx $
b0 #
1!
#1320
b1111111010 #
0!
#1330
b1111000111 $
b1001011 #
1!
#1340
b110100 #
0!
#1350
b110011 $
b1110000111 #
1!
#1360
b1110000001 #
0!
#1370
b1111001101 $
b1111001 #
1!
#1380
b11001011 #
0!
#1390
b111001 $
b1110110101 #
1!
#1400
b1100000111 #
0!
#1410
b0 $
b0 #
1!
#1420
b11111001 #
0!
#1430
b1111000111 $
b1001011 #
1!
#1440
b1100110101 #
0!
#1450
b110011 $
b1110000111 #
1!
#1460
b10000000 #
0!
#1470
b1111001101 $
b1111001 #
1!
#1480
b1111001100 #
0!
#1490
b111001 $
b1110110101 #
1!
#1500
b110 #
0!
#1510
b0 $
b0 #
1!
#1520
b1111111010 #
0!
#1530
b1111000111 $
b1001011 #
1!
#1540
b110100 #
0!
#1550
b110011 $
b1110000111 #
1!
#1560
b1110000001 #
0!
#1570
b1111001101 $
b1111001 #
1!
#1580
b11001011 #
0!
#1590
b111001 $
b1110110101 #
1!
#1600
b1100000111 #
0!
#1610
b0 $
b0 #
1!
#1620
b11111001 #
0!
#1630
b1111000111 $
b1001011 #
1!
#1640
b1100110101 #
0!
#1650
b110011 $
b1110000111 #
1!
#1660
b1111111 #
0!
#1670
b1111001101 $
b1111001 #
1!
#1680
b1111001100 #
0!
#1690
b111001 $
b1110110101 #
1!
#1700
b110 #
0!
#1710
b0 $
b0 #
1!
#1720
b1111111010 #
0!
#1730
b1111000111 $
b1001011 #
1!
#1740
b110100 #
0!
#1750
b110011 $
b1110000111 #
1!
#1760
b1110000001 #
0!
#1770
b1111001101 $
b1111001 #
1!
#1780
b11001011 #
0!
#1790
b111001 $
b1110110101 #
1!
#1800
b1100000111 #
0!
#1810
b0 $
b0 #
1!
#1820
b11111001 #
0!
#1830
b1111000111 $
b1001011 #
1!
#1840
b1100110101 #
0!
#1850
b110011 $
b1110000111 #
1!
#1860
b1111111 #
0!
#1870
b1111001101 $
b1111001 #
1!
#1880
b1111001100 #
0!
#1890
b111001 $
b1110110101 #
1!
#1900
b110 #
0!
#1910
b0 $
b0 #
1!
#1920
b1111111010 #
0!
#1930
b1111000111 $
b1001011 #
1!
#1940
b110100 #
0!
#1950
b110011 $
b1110000111 #
1!
#1960
b1110000001 #
0!
#1970
b1111001101 $
b1111001 #
1!
#1980
b11001011 #
0!
#1990
b111001 $
b1110110101 #
1!
#2000
b1100000111 #
0!
#2010
b0 $
b0 #
1!
#2020
b11111001 #
0!
#2030
b1111000111 $
b1001011 #
1!
#2040
b1100110101 #
0!
#2050
b110011 $
b1110000111 #
1!
#2060
b10000000 #
0!
#2070
b1111001101 $
b1111001 #
1!
#2080
b1111001100 #
0!
#2090
b111001 $
b1110110101 #
1!
#2100
b110 #
0!
#2110
b0 $
b0 #
1!
#2120
b1111111010 #
0!
#2130
b1111000111 $
b1001011 #
1!
#2140
b110100 #
0!
#2150
b110011 $
b1110000111 #
1!
#2160
b1110000000 #
0!
#2170
b1111001101 $
b1111001 #
1!
#2180
b11001011 #
0!
#2190
b111001 $
b1110110101 #
1!
#2200
b1100000111 #
0!
#2210
b0 $
b0 #
1!
#2220
b11111001 #
0!
#2230
b1111000111 $
b1001011 #
1!
#2240
b1100110101 #
0!
#2250
b110011 $
b1110000111 #
1!
#2260
b1111111 #
0!
#2270
b1111001101 $
b1111001 #
1!
#2280
b1111001100 #
0!
#2290
b111001 $
b1110110101 #
1!
#2300
b110 #
0!
#2310
b0 $
b0 #
1!
#2320
b1111111010 #
0!
#2330
b1111000111 $
b1001011 #
1!
#2340
b110100 #
0!
#2350
b110011 $
b1110000111 #
1!
#2360
b1110000001 #
0!
#2370
b1111001101 $
b1111001 #
1!
#2380
b11001011 #
0!
#2390
b111001 $
b1110110101 #
1!
#2400
b1100000111 #
0!
#2410
b0 $
b0 #
1!
#2420
b11111001 #
0!
#2430
b1111000111 $
b1001011 #
1!
#2440
b1100110101 #
0!
#2450
b110011 $
b1110000111 #
1!
#2460
b10000000 #
0!
#2470
b1111001101 $
b1111001 #
1!
#2480
b1111001100 #
0!
#2490
b111001 $
b1110110101 #
1!
#2500
b110 #
0!
#2510
b0 $
b0 #
1!
#2520
b1111111010 #
0!
#2530
b1111000111 $
b1001011 #
1!
#2540
b110100 #
0!
#2550
b110011 $
b1110000111 #
1!
#2560
b1110000000 #
0!
#2570
b1111001101 $
b1111001 #
1!
#2580
b11001011 #
0!
#2590
b111001 $
b1110110101 #
1!
#2600
b1100000111 #
0!
#2610
b0 $
b0 #
1!
#2620
b11111001 #
0!
#2630
b1111000111 $
b1001011 #
1!
#2640
b1100110101 #
0!
#2650
b110011 $
b1110000111 #
1!
#2660
b1111111 #
0!
#2670
b1111001101 $
b1111001 #
1!
#2680
b1111001100 #
0!
#2690
b111001 $
b1110110101 #
1!
#2700
b110 #
0!
#2710
b0 $
b0 #
1!
#2720
b1111111010 #
0!
#2730
b1111000111 $
b1001011 #
1!
#2740
b110100 #
0!
#2750
b110011 $
b1110000111 #
1!
#2760
b1110000001 #
0!
#2770
b1111001101 $
b1111001 #
1!
#2780
b11001011 #
0!
#2790
b111001 $
b1110110101 #
1!
#2800
b1100000111 #
0!
#2810
b0 $
b0 #
1!
#2820
b11111001 #
0!
#2830
b1111000111 $
b1001011 #
1!
#2840
b1100110101 #
0!
#2850
b110011 $
b1110000111 #
1!
#2860
b10000000 #
0!
#2870
b1111001101 $
b1111001 #
1!
#2880
b1111001100 #
0!
#2890
b111001 $
b1110110101 #
1!
#2900
b110 #
0!
#2910
b0 $
b0 #
1!
#2920
b1111111010 #
0!
#2930
b1111000111 $
b1001011 #
1!
#2940
b110100 #
0!
#2950
b110011 $
b1110000111 #
1!
#2960
b1110000000 #
0!
#2970
b1111001101 $
b1111001 #
1!
#2980
b11001011 #
0!
#2990
b111001 $
b1110110101 #
1!
#3000
b1100000111 #
0!
#3010
b0 $
b0 #
1!
#3020
b11111001 #
0!
#3030
b1111000111 $
b1001011 #
1!
#3040
b1100110101 #
0!
#3050
b110011 $
b1110000111 #
1!
#3060
b1111111 #
0!
#3070
b1111001101 $
b1111001 #
1!
#3080
b1111001100 #
0!
#3090
b111001 $
b1110110101 #
1!
#3100
b110 #
0!
#3110
b0 $
b0 #
1!
#3120
b1111111010 #
0!
#3130
b1111000111 $
b1001011 #
1!
#3140
b110100 #
0!
#3150
b110011 $
b1110000111 #
1!
#3160
b1110000001 #
0!
#3170
b1111001101 $
b1111001 #
1!
#3180
b11001011 #
0!
#3190
b111001 $
b1110110101 #
1!
#3200
b1100000111 #
0!
#3210
b0 $
b0 #
1!
#3220
b11111001 #
0!
#3230
b1111000111 $
b1001011 #
1!
#3240
b1100110101 #
0!
#3250
b110011 $
b1110000111 #
1!
#3260
b10000000 #
0!
#3270
b1111001101 $
b1111001 #
1!
#3280
b1111001100 #
0!
#3290
b111001 $
b1110110101 #
1!
#3300
b110 #
0!
#3310
b0 $
b0 #
1!
#3320
b1111111010 #
0!
#3330
b1111000111 $
b1001011 #
1!
#3340
b110100 #
0!
#3350
b110011 $
b1110000111 #
1!
#3360
b1110000001 #
0!
#3370
b1111001101 $
b1111001 #
1!
#3380
b11001011 #
0!
#3390
b111001 $
b1110110101 #
1!
#3400
b1100000111 #
0!
#3410
b0 $
b0 #
1!
#3420
b11111001 #
0!
#3430
b1111000111 $
b1001011 #
1!
#3440
b1100110101 #
0!
#3450
b110011 $
b1110000111 #
1!
#3460
b10000000 #
0!
#3470
b1111001101 $
b1111001 #
1!
#3480
b1111001100 #
0!
#3490
b111001 $
b1110110101 #
1!
#3500
b110 #
0!
#3510
b0 $
b0 #
1!
#3520
b1111111010 #
0!
#3530
b1111000111 $
b1001011 #
1!
#3540
b110100 #
0!
#3550
b110011 $
b1110000111 #
1!
#3560
b1110000001 #
0!
#3570
b1111001101 $
b1111001 #
1!
#3580
b11001011 #
0!
#3590
b111001 $
b1110110101 #
1!
#3600
b1100000111 #
0!
#3610
b0 $
b0 #
1!
#3620
b11111001 #
0!
#3630
b1111000111 $
b1001011 #
1!
#3640
b1100110101 #
0!
#3650
b110011 $
b1110000111 #
1!
#3660
b10000000 #
0!
#3670
b1111001101 $
b1111001 #
1!
#3680
b1111001100 #
0!
#3690
b111001 $
b1110110101 #
1!
#3700
b110 #
0!
#3710
b0 $
b0 #
1!
#3720
b1111111010 #
0!
#3730
b1111000111 $
b1001011 #
1!
#3740
b110100 #
0!
#3750
b110011 $
b1110000111 #
1!
#3760
b1110000000 #
0!
#3770
b1111001101 $
b1111001 #
1!
#3780
b11001011 #
0!
#3790
b111001 $
b1110110101 #
1!
#3800
b1100000111 #
0!
#3810
b0 $
b0 #
1!
#3820
b11111001 #
0!
#3830
b1111000111 $
b1001011 #
1!
#3840
b1100110101 #
0!
#3850
b110011 $
b1110000111 #
1!
#3860
b1111111 #
0!
#3870
b1111001101 $
b1111001 #
1!
#3880
b1111001100 #
0!
#3890
b111001 $
b1110110101 #
1!
#3900
b110 #
0!
#3910
b0 $
b0 #
1!
#3920
b1111111010 #
0!
#3930
b1111000111 $
b1001011 #
1!
#3940
b110100 #
0!
#3950
b110011 $
b1110000111 #
1!
#3960
b1110000001 #
0!
#3970
b1111001101 $
b1111001 #
1!
#3980
b11001011 #
0!
#3990
b111001 $
b1110110101 #
1!
#4000
b1100000111 #
0!
#4010
b0 $
b0 #
1!
#4020
b11111001 #
0!
#4030
b1111000111 $
b1001011 #
1!
#4040
b1100110101 #
0!
#4050
b110011 $
b1110000111 #
1!
#4060
b10000000 #
0!
#4070
b1111001101 $
b1111001 #
1!
#4080
b1111001100 #
0!
#4090
b111001 $
b1110110101 #
1!
#4100
b110 #
0!
#4110
b0 $
b0 #
1!
#4120
b1111111010 #
0!
#4130
b1111000111 $
b1001011 #
1!
#4140
b110100 #
0!
#4150
b110011 $
b1110000111 #
1!
#4160
b1110000001 #
0!
#4170
b1111001101 $
b1111001 #
1!
#4180
b11001011 #
0!
#4190
b111001 $
b1110110101 #
1!
#4200
b1100000111 #
0!
#4210
b0 $
b0 #
1!
#4220
b11111001 #
0!
#4230
b1111000111 $
b1001011 #
1!
#4240
b1100110101 #
0!
#4250
b110011 $
b1110000111 #
1!
#4260
b1111111 #
0!
#4270
b1111001101 $
b1111001 #
1!
#4280
b1111001100 #
0!
#4290
b111001 $
b1110110101 #
1!
#4300
b110 #
0!
#4310
b0 $
b0 #
1!
#4320
b1111111010 #
0!
#4330
b1111000111 $
b1001011 #
1!
#4340
b110100 #
0!
#4350
b110011 $
b1110000111 #
1!
#4360
b1110000001 #
0!
#4370
b1111001101 $
b1111001 #
1!
#4380
b11001011 #
0!
#4390
b111001 $
b1110110101 #
1!
#4400
b1100000111 #
0!
#4410
b0 $
b0 #
1!
#4420
b11111001 #
0!
#4430
b1111000111 $
b1001011 #
1!
#4440
b1100110101 #
0!
#4450
b110011 $
b1110000111 #
1!
#4460
b10000000 #
0!
#4470
b1111001101 $
b1111001 #
1!
#4480
b1111001100 #
0!
#4490
b111001 $
b1110110101 #
1!
#4500
b110 #
0!
#4510
b0 $
b0 #
1!
#4520
b1111111010 #
0!
#4530
b1111000111 $
b1001011 #
1!
#4540
b110100 #
0!
#4550
b110011 $
b1110000111 #
1!
#4560
b1110000000 #
0!
#4570
b1111001101 $
b1111001 #
1!
#4580
b11001011 #
0!
#4590
b111001 $
b1110110101 #
1!
#4600
b1100000111 #
0!
#4610
b0 $
b0 #
1!
#4620
b11111001 #
0!
#4630
b1111000111 $
b1001011 #
1!
#4640
b1100110101 #
0!
#4650
b110011 $
b1110000111 #
1!
#4660
b10000000 #
0!
#4670
b1111001101 $
b1111001 #
1!
#4680
b1111001100 #
0!
#4690
b111001 $
b1110110101 #
1!
#4700
b110 #
0!
#4710
b0 $
b0 #
1!
#4720
b1111111010 #
0!
#4730
b1111000111 $
b1001011 #
1!
#4740
b110100 #
0!
#4750
b110011 $
b1110000111 #
1!
#4760
b1110000000 #
0!
#4770
b1111001101 $
b1111001 #
1!
#4780
b11001011 #
0!
#4790
b111001 $
b1110110101 #
1!
#4800
b1100000111 #
0!
#4810
b0 $
b0 #
1!
#4820
b11111001 #
0!
#4830
b1111000111 $
b1001011 #
1!
#4840
b1100110101 #
0!
#4850
b110011 $
b1110000111 #
1!
#4860
b1111111 #
0!
#4870
b1111001101 $
b1111001 #
1!
#4880
b1111001100 #
0!
#4890
b111001 $
b1110110101 #
1!
#4900
b110 #
0!
#4910
b0 $
b0 #
1!
#4920
b1111111010 #
0!
#4930
b1111000111 $
b1001011 #
1!
#4940
b110100 #
0!
#4950
b110011 $
b1110000111 #
1!
#4960
b1110000001 #
0!
#4970
b1111001101 $
b1111001 #
1!
#4980
b11001011 #
0!
#4990
b111001 $
b1110110101 #
1!
#5000
b1100000111 #
0!
#5010
b0 $
b0 #
1!
#5020
b11111001 #
0!
#5030
b1111000111 $
b1001011 #
1!
#5040
b1100110101 #
0!
#5050
b110011 $
b1110000111 #
1!
#5060
b1111111 #
0!
#5070
b1111001101 $
b1111001 #
1!
#5080
b1111001100 #
0!
#5090
b111001 $
b1110110101 #
1!
#5100
b110 #
0!
#5110
b0 $
b0 #
1!
#5120
b1111111010 #
0!
#5130
b1111000111 $
b1001011 #
1!
#5140
b110100 #
0!
#5150
b110011 $
b1110000111 #
1!
#5160
b1110000001 #
0!
#5170
b1111001101 $
b1111001 #
1!
#5180
b11001011 #
0!
#5190
b111001 $
b1110110101 #
1!
#5200
b1100000111 #
0!
#5210
b0 $
b0 #
1!
#5220
b11111001 #
0!
#5230
b1111000111 $
b1001011 #
1!
#5240
b1100110101 #
0!
#5250
b110011 $
b1110000111 #
1!
#5260
b10000000 #
0!
#5270
b1111001101 $
b1111001 #
1!
#5280
b1111001100 #
0!
#5290
b111001 $
b1110110101 #
1!
#5300
b110 #
0!
#5310
b0 $
b0 #
1!
#5320
b1111111010 #
0!
#5330
b1111000111 $
b1001011 #
1!
#5340
b110100 #
0!
#5350
b110011 $
b1110000111 #
1!
#5360
b1110000001 #
0!
#5370
b1111001101 $
b1111001 #
1!
#5380
b11001011 #
0!
#5390
b111001 $
b1110110101 #
1!
#5400
b1100000111 #
0!
#5410
b0 $
b0 #
1!
#5420
b11111001 #
0!
#5430
b1111000111 $
b1001011 #
1!
#5440
b1100110101 #
0!
#5450
b110011 $
b1110000111 #
1!
#5460
b10000000 #
0!
#5470
b1111001101 $
b1111001 #
1!
#5480
b1111001100 #
0!
#5490
b111001 $
b1110110101 #
1!
#5500
b110 #
0!
#5510
b0 $
b0 #
1!
#5520
b1111111010 #
0!
#5530
b1111000111 $
b1001011 #
1!
#5540
b110100 #
0!
#5550
b110011 $
b1110000111 #
1!
#5560
b1110000001 #
0!
#5570
b1111001101 $
b1111001 #
1!
#5580
b11001011 #
0!
#5590
b111001 $
b1110110101 #
1!
#5600
b1100000111 #
0!
#5610
b0 $
b0 #
1!
#5620
b11111001 #
0!
#5630
b1111000111 $
b1001011 #
1!
#5640
b1100110101 #
0!
#5650
b110011 $
b1110000111 #
1!
#5660
b10000000 #
0!
#5670
b1111001101 $
b1111001 #
1!
#5680
b1111001100 #
0!
#5690
b111001 $
b1110110101 #
1!
#5700
b110 #
0!
#5710
b0 $
b0 #
1!
#5720
b1111111010 #
0!
#5730
b1111000111 $
b1001011 #
1!
#5740
b110100 #
0!
#5750
b110011 $
b1110000111 #
1!
#5760
b1110000001 #
0!
#5770
b1111001101 $
b1111001 #
1!
#5780
b11001011 #
0!
#5790
b111001 $
b1110110101 #
1!
#5800
b1100000111 #
0!
#5810
b0 $
b0 #
1!
#5820
b11111001 #
0!
#5830
b1111000111 $
b1001011 #
1!
#5840
b1100110101 #
0!
#5850
b110011 $
b1110000111 #
1!
#5860
b1111111 #
0!
#5870
b1111001101 $
b1111001 #
1!
#5880
b1111001100 #
0!
#5890
b111001 $
b1110110101 #
1!
#5900
b110 #
0!
#5910
b0 $
b0 #
1!
#5920
b1111111010 #
0!
#5930
b1111000111 $
b1001011 #
1!
#5940
b110100 #
0!
#5950
b110011 $
b1110000111 #
1!
#5960
b1110000000 #
0!
#5970
b1111001101 $
b1111001 #
1!
#5980
b11001011 #
0!
#5990
b111001 $
b1110110101 #
1!
#6000
b1100000111 #
0!
#6010
b0 $
b0 #
1!
#6020
b11111001 #
0!
#6030
b1111000111 $
b1001011 #
1!
#6040
b1100110101 #
0!
#6050
b110011 $
b1110000111 #
1!
#6060
b10000000 #
0!
#6070
b1111001101 $
b1111001 #
1!
#6080
b1111001100 #
0!
#6090
b111001 $
b1110110101 #
1!
#6100
b110 #
0!
#6110
b0 $
b0 #
1!
#6120
b1111111010 #
0!
#6130
b1111000111 $
b1001011 #
1!
#6140
b110100 #
0!
#6150
b110011 $
b1110000111 #
1!
#6160
b1110000000 #
0!
#6170
b1111001101 $
b1111001 #
1!
#6180
b11001011 #
0!
#6190
b111001 $
b1110110101 #
1!
#6200
b1100000111 #
0!
#6210
b0 $
b0 #
1!
#6220
b11111001 #
0!
#6230
b1111000111 $
b1001011 #
1!
#6240
b1100110101 #
0!
#6250
b110011 $
b1110000111 #
1!
#6260
b10000000 #
0!
#6270
b1111001101 $
b1111001 #
1!
#6280
b1111001100 #
0!
#6290
b111001 $
b1110110101 #
1!
#6300
b110 #
0!
#6310
b0 $
b0 #
1!
#6320
b1111111010 #
0!
#6330
b1111000111 $
b1001011 #
1!
#6340
b110100 #
0!
#6350
b110011 $
b1110000111 #
1!
#6360
b1110000000 #
0!
#6370
b1111001101 $
b1111001 #
1!
#6380
b11001011 #
0!
#6390
b111001 $
b1110110101 #
1!
#6400
b1100000111 #
0!
#6410
b0 $
b0 #
1!
#6420
b11111001 #
0!
#6430
b1111000111 $
b1001011 #
1!
#6440
b1100110101 #
0!
#6450
b110011 $
b1110000111 #
1!
#6460
b10000000 #
0!
#6470
b1111001101 $
b1111001 #
1!
#6480
b1111001100 #
0!
#6490
b111001 $
b1110110101 #
1!
#6500
b110 #
0!
#6510
b0 $
b0 #
1!
#6520
b1111111010 #
0!
#6530
b1111000111 $
b1001011 #
1!
#6540
b110100 #
0!
#6550
b110011 $
b1110000111 #
1!
#6560
b1110000001 #
0!
#6570
b1111001101 $
b1111001 #
1!
#6580
b11001011 #
0!
#6590
b111001 $
b1110110101 #
1!
#6600
b1100000111 #
0!
#6610
b0 $
b0 #
1!
#6620
b11111001 #
0!
#6630
b1111000111 $
b1001011 #
1!
#6640
b1100110101 #
0!
#6650
b110011 $
b1110000111 #
1!
#6660
b10000000 #
0!
#6670
b1111001101 $
b1111001 #
1!
#6680
b1111001100 #
0!
#6690
b111001 $
b1110110101 #
1!
#6700
b110 #
0!
#6710
b0 $
b0 #
1!
#6720
b1111111010 #
0!
#6730
b1111000111 $
b1001011 #
1!
#6740
b110100 #
0!
#6750
b110011 $
b1110000111 #
1!
#6760
b1110000001 #
0!
#6770
b1111001101 $
b1111001 #
1!
#6780
b11001011 #
0!
#6790
b111001 $
b1110110101 #
1!
#6800
b1100000111 #
0!
#6810
b0 $
b0 #
1!
#6820
b11111001 #
0!
#6830
b1111000111 $
b1001011 #
1!
#6840
b1100110101 #
0!
#6850
b110011 $
b1110000111 #
1!
#6860
b10000000 #
0!
#6870
b1111001101 $
b1111001 #
1!
#6880
b1111001100 #
0!
#6890
b111001 $
b1110110101 #
1!
#6900
b110 #
0!
#6910
b0 $
b0 #
1!
#6920
b1111111010 #
0!
#6930
b1111000111 $
b1001011 #
1!
#6940
b110100 #
0!
#6950
b110011 $
b1110000111 #
1!
#6960
b1110000001 #
0!
#6970
b1111001101 $
b1111001 #
1!
#6980
b11001011 #
0!
#6990
b111001 $
b1110110101 #
1!
#7000
b1100000111 #
0!
#7010
b0 $
b0 #
1!
#7020
b11111001 #
0!
#7030
b1111000111 $
b1001011 #
1!
#7040
b1100110101 #
0!
#7050
b110011 $
b1110000111 #
1!
#7060
b1111111 #
0!
#7070
b1111001101 $
b1111001 #
1!
#7080
b1111001100 #
0!
#7090
b111001 $
b1110110101 #
1!
#7100
b110 #
0!
#7110
b0 $
b0 #
1!
#7120
b1111111010 #
0!
#7130
b1111000111 $
b1001011 #
1!
#7140
b110100 #
0!
#7150
b110011 $
b1110000111 #
1!
#7160
b1110000000 #
0!
#7170
b1111001101 $
b1111001 #
1!
#7180
b11001011 #
0!
#7190
b111001 $
b1110110101 #
1!
#7200
b1100000111 #
0!
#7210
b0 $
b0 #
1!
#7220
b11111001 #
0!
#7230
b1111000111 $
b1001011 #
1!
#7240
b1100110101 #
0!
#7250
b110011 $
b1110000111 #
1!
#7260
b1111111 #
0!
#7270
b1111001101 $
b1111001 #
1!
#7280
b1111001100 #
0!
#7290
b111001 $
b1110110101 #
1!
#7300
b110 #
0!
#7310
b0 $
b0 #
1!
#7320
b1111111010 #
0!
#7330
b1111000111 $
b1001011 #
1!
#7340
b110100 #
0!
#7350
b110011 $
b1110000111 #
1!
#7360
b1110000001 #
0!
#7370
b1111001101 $
b1111001 #
1!
#7380
b11001011 #
0!
#7390
b111001 $
b1110110101 #
1!
#7400
b1100000111 #
0!
#7410
b0 $
b0 #
1!
#7420
b11111001 #
0!
#7430
b1111000111 $
b1001011 #
1!
#7440
b1100110101 #
0!
#7450
b110011 $
b1110000111 #
1!
#7460
b1111111 #
0!
#7470
b1111001101 $
b1111001 #
1!
#7480
b1111001100 #
0!
#7490
b111001 $
b1110110101 #
1!
#7500
b110 #
0!
#7510
b0 $
b0 #
1!
#7520
b1111111010 #
0!
#7530
b1111000111 $
b1001011 #
1!
#7540
b110100 #
0!
#7550
b110011 $
b1110000111 #
1!
#7560
b1110000001 #
0!
#7570
b1111001101 $
b1111001 #
1!
#7580
b11001011 #
0!
